dbt/__init__.py
dbt/adapters/snowflake/__init__.py
dbt/adapters/snowflake/__version__.py
dbt/adapters/snowflake/auth.py
dbt/adapters/snowflake/column.py
dbt/adapters/snowflake/connections.py
dbt/adapters/snowflake/constants.py
dbt/adapters/snowflake/impl.py
dbt/adapters/snowflake/parse_model.py
dbt/adapters/snowflake/query_headers.py
dbt/adapters/snowflake/relation.py
dbt/adapters/snowflake/catalogs/__init__.py
dbt/adapters/snowflake/catalogs/_built_in.py
dbt/adapters/snowflake/catalogs/_iceberg_rest.py
dbt/adapters/snowflake/catalogs/_info_schema.py
dbt/adapters/snowflake/record/__init__.py
dbt/adapters/snowflake/record/handle.py
dbt/adapters/snowflake/record/cursor/cursor.py
dbt/adapters/snowflake/record/cursor/sfqid.py
dbt/adapters/snowflake/record/cursor/sqlstate.py
dbt/adapters/snowflake/relation_configs/__init__.py
dbt/adapters/snowflake/relation_configs/base.py
dbt/adapters/snowflake/relation_configs/dynamic_table.py
dbt/adapters/snowflake/relation_configs/policies.py
dbt/include/snowflake/__init__.py
dbt/include/snowflake/dbt_project.yml
dbt/include/snowflake/profile_template.yml
dbt/include/snowflake/macros/adapters.sql
dbt/include/snowflake/macros/apply_grants.sql
dbt/include/snowflake/macros/catalog.sql
dbt/include/snowflake/macros/get_custom_name.sql
dbt/include/snowflake/macros/metadata.sql
dbt/include/snowflake/macros/materializations/clone.sql
dbt/include/snowflake/macros/materializations/dynamic_table.sql
dbt/include/snowflake/macros/materializations/incremental.sql
dbt/include/snowflake/macros/materializations/seed.sql
dbt/include/snowflake/macros/materializations/snapshot.sql
dbt/include/snowflake/macros/materializations/table.sql
dbt/include/snowflake/macros/materializations/test.sql
dbt/include/snowflake/macros/materializations/view.sql
dbt/include/snowflake/macros/materializations/incremental/insert_overwrite.sql
dbt/include/snowflake/macros/materializations/incremental/merge.sql
dbt_snowflake-1.10.7.dist-info/METADATA
dbt_snowflake-1.10.7.dist-info/WHEEL
dbt_snowflake-1.10.7.dist-info/licenses/LICENSE
dbt_snowflake-1.10.7.dist-info/RECORD
