Metadata-Version: 2.4
Name: dbt-snowflake
Version: 1.10.7
Summary: The Snowflake adapter plugin for dbt
Project-URL: Homepage, https://github.com/dbt-labs/dbt-adapters/tree/main/dbt-snowflake
Project-URL: Documentation, https://docs.getdbt.com
Project-URL: Repository, https://github.com/dbt-labs/dbt-adapters.git#subdirectory=dbt-snowflake
Project-URL: Issues, https://github.com/dbt-labs/dbt-adapters/issues
Project-URL: Changelog, https://github.com/dbt-labs/dbt-adapters/blob/main/dbt-snowflake/CHANGELOG.md
Author-email: dbt Labs <info@dbtlabs.com>
Maintainer-email: dbt Labs <info@dbtlabs.com>
License-File: LICENSE
Keywords: adapter,adapters,database,dbt,dbt Cloud,dbt Core,dbt Labs,dbt-core,elt,snowflake
Classifier: Development Status :: 5 - Production/Stable
Classifier: License :: OSI Approved :: Apache Software License
Classifier: Operating System :: MacOS :: MacOS X
Classifier: Operating System :: Microsoft :: Windows
Classifier: Operating System :: POSIX :: Linux
Classifier: Programming Language :: Python :: 3.10
Classifier: Programming Language :: Python :: 3.11
Classifier: Programming Language :: Python :: 3.12
Requires-Python: >=3.10.0
Requires-Dist: agate
Requires-Dist: certifi<2025.4.26
Requires-Dist: dbt-adapters<2.0,>=1.22.4
Requires-Dist: dbt-common<2.0,>=1.10
Requires-Dist: dbt-core>=1.10.0rc0
Requires-Dist: snowflake-connector-python[secure-local-storage]<5.0.0,>=4.0.0
